radiomap/__init__.py
radiomap/cli.py
radiomap/_helpers/__init__.py
radiomap-0.0.1.2.dist-info/LICENSE.rst
radiomap-0.0.1.2.dist-info/METADATA
radiomap-0.0.1.2.dist-info/WHEEL
radiomap-0.0.1.2.dist-info/top_level.txt
radiomap-0.0.1.2.dist-info/RECORD
