Metadata-Version: 2.1
Name: radiomap
Version: 0.0.1.2
Summary: A python package which has radio astronomy calculation tools including spectral index map calculation.
Home-page: https://github.com/avialxee/radiomap
Author: Avinash Kumar
Author-email: avialxee@gmail.com
License: UNKNOWN
Project-URL: Bug Tracker, https://github.com/avialxee/radiomap/issues
Platform: UNKNOWN
Classifier: Programming Language :: Python :: 3.6
Classifier: Programming Language :: Python :: 3.7
Classifier: Programming Language :: Python :: 3.8
Classifier: Programming Language :: Python :: 3.9
Classifier: License :: OSI Approved :: BSD License
Classifier: Intended Audience :: Science/Research
Requires-Dist: astropy (>=4.2.1)
Requires-Dist: numpy (>=1.20.3)
Requires-Dist: astroquery
Provides-Extra: dev
Requires-Dist: pytest (>=3.7) ; extra == 'dev'
